ramqp/__init__.py
ramqp/abstract.py
ramqp/amqp.py
ramqp/config.py
ramqp/depends.py
ramqp/metrics.py
ramqp/mo.py
ramqp/py.typed
ramqp/utils.py
ramqp-9.3.0.dist-info/LICENSE
ramqp-9.3.0.dist-info/LICENSES/MPL-2.0.txt
ramqp-9.3.0.dist-info/METADATA
ramqp-9.3.0.dist-info/WHEEL
ramqp-9.3.0.dist-info/RECORD
