Metadata-Version: 2.1
Name: ramqp
Version: 9.3.0
Summary: Rammearkitektur AMQP library (aio_pika wrapper)
Home-page: https://magenta.dk/
License: MPL-2.0
Keywords: os2mo,amqp
Author: Magenta ApS
Author-email: info@magenta.dk
Requires-Python: >=3.10,<4.0
Classifier: License :: OSI Approved
Classifier: Programming Language :: Python :: 3
Classifier: Programming Language :: Python :: 3.10
Classifier: Programming Language :: Python :: 3.11
Classifier: Programming Language :: Python :: 3.12
Requires-Dist: aio-pika (>=8.3,<10.0)
Requires-Dist: anyio (>=3.6.2,<4.0.0)
Requires-Dist: fastapi (>=0.108.0,<1.0)
Requires-Dist: more-itertools (>=9.1.0,<10.0.0)
Requires-Dist: prometheus-client (>=0.16,<0.18)
Requires-Dist: pydantic (>=1.10.5,<2.0.0)
Requires-Dist: ra-utils (>=1.12.4,<2.0.0)
Requires-Dist: structlog (>=23.1.0,<24.0.0)
Project-URL: Repository, https://git.magenta.dk/rammearkitektur/ramqp
